components/__init__.py
components/data_ingestion.py
components/data_transformation.py
components/model_evaluation.py
components/model_trainer.py
mongodb_automation/__init__.py
mongodb_automation/mongo_crud.py
pipeline/__init__.py
pipeline/training_pipeline.py
utils/__init__.py
utils/utils.py
database_automated_connectivity-0.0.4.dist-info/LICENSE
database_automated_connectivity-0.0.4.dist-info/METADATA
database_automated_connectivity-0.0.4.dist-info/WHEEL
database_automated_connectivity-0.0.4.dist-info/top_level.txt
database_automated_connectivity-0.0.4.dist-info/RECORD
